forgellm/__init__.py
forgellm/__main__.py
forgellm/api/__init__.py
forgellm/api/routes.py
forgellm/api/validators.py
forgellm/cli/__init__.py
forgellm/cli/commands.py
forgellm/cli/main.py
forgellm/models/__init__.py
forgellm/models/load_model_helper.py
forgellm/models/model_fuser.py
forgellm/models/model_manager.py
forgellm/models/model_publisher.py
forgellm/models/model_quantizer.py
forgellm/server/__init__.py
forgellm/server/main.py
forgellm/training/__init__.py
forgellm/training/checkpointing.py
forgellm/training/config.py
forgellm/training/dashboard.py
forgellm/training/data_processor.py
forgellm/training/instruction_tuner.py
forgellm/training/lr_scheduler.py
forgellm/training/metrics_logger.py
forgellm/training/monitor.py
forgellm/training/process_manager.py
forgellm/training/realtime_monitor.py
forgellm/training/run_training.py
forgellm/training/trainer.py
forgellm/utils/__init__.py
forgellm/utils/model_architectures.py
forgellm/utils/process_tracker.py
forgellm/utils/text_stats.py
forgellm/web/__init__.py
forgellm/web/app.py
forgellm/web/main.py
forgellm/web/run.py
forgellm/web/routes/__init__.py
forgellm/web/routes/views.py
forgellm/web/services/__init__.py
forgellm/web/services/socket_service.py
forgellm/web/static/app.js
forgellm/web/static/favicon.ico
forgellm/web/static/css/styles.css
forgellm/web/static/js/components/compare.js
forgellm/web/static/js/components/dashboard.js
forgellm/web/static/js/components/generation.js
forgellm/web/static/js/components/models.js
forgellm/web/static/js/components/quantization.js
forgellm/web/static/js/services/api.js
forgellm/web/static/js/services/socket.js
forgellm/web/static/js/utils/charts.js
forgellm/web/static/js/utils/formatting.js
forgellm/web/static/js/utils/marked.min.js
forgellm/web/templates/index.html
forgellm-0.4.2.dist-info/licenses/LICENSE
forgellm-0.4.2.dist-info/METADATA
forgellm-0.4.2.dist-info/WHEEL
forgellm-0.4.2.dist-info/entry_points.txt
forgellm-0.4.2.dist-info/top_level.txt
forgellm-0.4.2.dist-info/RECORD
