Metadata-Version: 2.4
Name: forgellm
Version: 0.4.2
Summary: A comprehensive toolkit for end-to-end continued pre-training, fine-tuning, monitoring, testing and publishing of language models with MLX-LM
Author-email: Laurent-Philippe Albou <lpalbou@gmail.com>
License: MIT
Project-URL: Homepage, https://github.com/lpalbou/forgellm
Project-URL: Bug Tracker, https://github.com/lpalbou/forgellm/issues
Project-URL: Documentation, https://github.com/lpalbou/forgellm/tree/main/docs
Project-URL: Source Code, https://github.com/lpalbou/forgellm
Keywords: llm,language-models,machine-learning,mlx,mlx-lm,fine-tuning,pre-training
Classifier: Programming Language :: Python :: 3
Classifier: Programming Language :: Python :: 3.8
Classifier: Programming Language :: Python :: 3.9
Classifier: Programming Language :: Python :: 3.10
Classifier: Programming Language :: Python :: 3.11
Classifier: License :: OSI Approved :: MIT License
Classifier: Operating System :: OS Independent
Classifier: Development Status :: 3 - Alpha
Classifier: Intended Audience :: Developers
Classifier: Intended Audience :: Science/Research
Classifier: Topic :: Scientific/Engineering :: Artificial Intelligence
Requires-Python: >=3.8
License-File: LICENSE
Requires-Dist: mlx-lm>=0.0.3
Requires-Dist: mlx>=0.0.7
Requires-Dist: numpy>=1.20.0
Requires-Dist: flask>=2.0.0
Requires-Dist: flask-socketio>=5.0.0
Requires-Dist: plotly>=5.0.0
Requires-Dist: psutil>=5.8.0
Requires-Dist: huggingface-hub>=0.12.0
Requires-Dist: matplotlib>=3.4.0
Requires-Dist: filelock>=3.0.0
Provides-Extra: dev
Requires-Dist: pytest>=6.0.0; extra == "dev"
Requires-Dist: black>=22.0.0; extra == "dev"
Requires-Dist: isort>=5.0.0; extra == "dev"
Requires-Dist: mypy>=0.900; extra == "dev"
Requires-Dist: build>=0.10.0; extra == "dev"
Requires-Dist: twine>=4.0.0; extra == "dev"
Dynamic: license-file
